google/cloud/bare_metal_solution/__init__.py
google/cloud/bare_metal_solution/gapic_version.py
google/cloud/bare_metal_solution/py.typed
google/cloud/bare_metal_solution_v2/__init__.py
google/cloud/bare_metal_solution_v2/gapic_metadata.json
google/cloud/bare_metal_solution_v2/gapic_version.py
google/cloud/bare_metal_solution_v2/py.typed
google/cloud/bare_metal_solution_v2/services/__init__.py
google/cloud/bare_metal_solution_v2/services/bare_metal_solution/__init__.py
google/cloud/bare_metal_solution_v2/services/bare_metal_solution/async_client.py
google/cloud/bare_metal_solution_v2/services/bare_metal_solution/client.py
google/cloud/bare_metal_solution_v2/services/bare_metal_solution/pagers.py
google/cloud/bare_metal_solution_v2/services/bare_metal_solution/transports/__init__.py
google/cloud/bare_metal_solution_v2/services/bare_metal_solution/transports/base.py
google/cloud/bare_metal_solution_v2/services/bare_metal_solution/transports/grpc.py
google/cloud/bare_metal_solution_v2/services/bare_metal_solution/transports/grpc_asyncio.py
google/cloud/bare_metal_solution_v2/services/bare_metal_solution/transports/rest.py
google/cloud/bare_metal_solution_v2/services/bare_metal_solution/transports/rest_base.py
google/cloud/bare_metal_solution_v2/types/__init__.py
google/cloud/bare_metal_solution_v2/types/baremetalsolution.py
google/cloud/bare_metal_solution_v2/types/common.py
google/cloud/bare_metal_solution_v2/types/instance.py
google/cloud/bare_metal_solution_v2/types/lun.py
google/cloud/bare_metal_solution_v2/types/network.py
google/cloud/bare_metal_solution_v2/types/nfs_share.py
google/cloud/bare_metal_solution_v2/types/osimage.py
google/cloud/bare_metal_solution_v2/types/provisioning.py
google/cloud/bare_metal_solution_v2/types/ssh_key.py
google/cloud/bare_metal_solution_v2/types/volume.py
google/cloud/bare_metal_solution_v2/types/volume_snapshot.py
google_cloud_bare_metal_solution-1.12.0.dist-info/licenses/LICENSE
google_cloud_bare_metal_solution-1.12.0.dist-info/METADATA
google_cloud_bare_metal_solution-1.12.0.dist-info/WHEEL
google_cloud_bare_metal_solution-1.12.0.dist-info/top_level.txt
google_cloud_bare_metal_solution-1.12.0.dist-info/RECORD
